gns3fy/__init__.py
gns3fy/drawing_utils.py
gns3fy/gns3fy.py
gns3fy-0.7.2.dist-info/METADATA
gns3fy-0.7.2.dist-info/WHEEL
gns3fy-0.7.2.dist-info/RECORD
