Metadata-Version: 2.1
Name: gns3fy
Version: 0.7.2
Summary: Python wrapper around GNS3 Server API
Home-page: https://github.com/davidban77/gns3fy
License: MIT
Keywords: network,gns3,python,restapi,netdev
Author: David Flores
Author-email: davidflores7_8@hotmail.com
Requires-Python: >=3.6,<4.0
Classifier: License :: OSI Approved :: MIT License
Classifier: Programming Language :: Python :: 3
Classifier: Programming Language :: Python :: 3.6
Classifier: Programming Language :: Python :: 3.7
Classifier: Programming Language :: Python :: 3.8
Classifier: Programming Language :: Python :: 3.9
Classifier: Programming Language :: Python :: 3.10
Classifier: Programming Language :: Python :: 3.11
Requires-Dist: pydantic (>=1.0,<2.0)
Requires-Dist: requests (>=2.22,<3.0)
Project-URL: Repository, https://github.com/davidban77/gns3fy
